[
    {
      "id": 1,
      "name": "Kiki",
      "image": "https://vignette.wikia.nocookie.net/studio-ghibli/images/4/4a/Kiki.png/revision/latest?cb=20110713230554",
      "count": 0
    },
    {
      "id": 2,
      "name": "Howl",
      "image": "https://vignette.wikia.nocookie.net/studio-ghibli/images/1/1b/Howl.png/revision/latest?cb=20110702010034",
      "count": 0
    },
    {
      "id": 3,
      "name": "Sophie",
      "image": "https://vignette.wikia.nocookie.net/studio-ghibli/images/6/6d/Sophie.jpg/revision/latest?cb=20110701082816",
      "count": 0
    },
    {
      "id": 4,
      "name": "Granmammare",
      "image": "https://vignette.wikia.nocookie.net/studio-ghibli/images/4/43/Granmammare.png/revision/latest?cb=20181029034955",
      "count": 0
    },
    {
      "id": 5,
      "name": "San",
      "image": "https://vignette.wikia.nocookie.net/studio-ghibli/images/4/4b/San_%282%29.jpg/revision/latest?cb=20110702000009",
      "count": 0
    },
    {
      "id": 6,
      "name": "Chihiro",
      "image": "https://vignette.wikia.nocookie.net/studio-ghibli/images/6/69/Chihiro.jpg/revision/latest?cb=20181022234927",
      "count": 0
    },
    {
      "id": 7,
      "name": "Totoro",
      "image": "https://vignette.wikia.nocookie.net/studio-ghibli/images/5/53/Totoro.jpg/revision/latest?cb=20180107143036",
      "count": 0
    },
    {
      "id": 8,
      "name": "Arietty",
      "image": "https://vignette.wikia.nocookie.net/studio-ghibli/images/d/d7/Arrietty_%282%29.png/revision/latest?cb=20111230012557",
      "count": 0
    }
  ]